Metadata-Version: 1.1
Name: prettytraceback
Version: 0.2.0
Summary: Python plugin for enabling pretty tracebacks
Home-page: UNKNOWN
Author: Tom Flanagan
Author-email: tom@zkpq.ca
License: MIT
Keywords: python traceback cgitb color colors pretty shel tool ipython ultratb
Platform: UNKNOWN
Classifier: Intended Audience :: Developers
Classifier: License :: OSI Approved :: MIT License
Classifier: Operating System :: OS Independent
Classifier: Programming Language :: Python
Classifier: Programming Language :: Python :: 2
Classifier: Programming Language :: Python :: 2.7
Classifier: Programming Language :: Python :: 3
Classifier: Programming Language :: Python :: 3.3
Classifier: Programming Language :: Python :: 3.4
Classifier: Programming Language :: Python :: 3.5
Classifier: Programming Language :: Python :: Implementation :: PyPy
